MANIFEST.in
README.md
setup.py
idiffuse/__init__.py
idiffuse/diffuser.py
idiffuse/photometry.py
idiffuse/telescope.py
idiffuse.egg-info/PKG-INFO
idiffuse.egg-info/SOURCES.txt
idiffuse.egg-info/dependency_links.txt
idiffuse.egg-info/requires.txt
idiffuse.egg-info/top_level.txt
idiffuse/filters/arctic_qe.txt
idiffuse/filters/bess-b.txt
idiffuse/filters/bess-i.txt
idiffuse/filters/bess-r.txt
idiffuse/filters/bess-u.txt
idiffuse/filters/bess-v.txt
idiffuse/filters/semrock_857_30.txt
idiffuse/filters/sloan_g_filter.txt
idiffuse/filters/sloan_i_filter.txt
idiffuse/filters/sloan_r_filter.txt
idiffuse/filters/sloan_z_filter.txt