Metadata-Version: 1.1
Name: idiffuse
Version: 0.0.1
Summary: A tool to calculate on-sky diffuser-assisted photometric precisions
Home-page: https://github.com/gummiks/idiffuse
Author: Gudmundur Stefansson
Author-email: gummiks@gmail.com
License: GPLv3
Keywords: Diffusers Photometry Astronomy
Platform: UNKNOWN
Classifier: Topic :: Scientific/Engineering :: Astronomy
